doccsy/__init__.py
doccsy/ai_explain.py
doccsy/doccsy.py
doccsy/menu.py
doccsy/parser_js.py
doccsy/parser_lua.py
doccsy/parser_php.py
doccsy-1.0.dist-info/METADATA
doccsy-1.0.dist-info/WHEEL
doccsy-1.0.dist-info/entry_points.txt
doccsy-1.0.dist-info/top_level.txt
doccsy-1.0.dist-info/RECORD
