Metadata-Version: 2.4
Name: doccsy
Version: 1.0
Summary: Generate GitBook-ready Markdown docs from code comments in Lua, JavaScript, and PHP files.
Author: No-Brainer
Requires-Dist: typer
Requires-Dist: requests
Requires-Dist: questionary
Dynamic: author
Dynamic: requires-dist
Dynamic: summary
